circuits_bricks/__init__.py
circuits_bricks/version.py
circuits_bricks/app/__init__.py
circuits_bricks/app/application.py
circuits_bricks/app/config.py
circuits_bricks/app/logger.py
circuits_bricks/core/__init__.py
circuits_bricks/core/timers.py
circuits_bricks/misc/__init__.py
circuits_bricks/misc/compquery.py
circuits_bricks/net/__init__.py
circuits_bricks/net/sockets.py
circuits_bricks/web/__init__.py
circuits_bricks/web/client.py
circuits_bricks/web/misc.py
circuits_bricks/web/sessions.py
circuits_bricks/web/wsgi.py
circuits_bricks/web/dispatchers/__init__.py
circuits_bricks/web/dispatchers/dispatcher.py
circuits_bricks-0.4.4.dist-info/DESCRIPTION.rst
circuits_bricks-0.4.4.dist-info/METADATA
circuits_bricks-0.4.4.dist-info/RECORD
circuits_bricks-0.4.4.dist-info/WHEEL
circuits_bricks-0.4.4.dist-info/metadata.json
circuits_bricks-0.4.4.dist-info/top_level.txt
tests/ConfigBasic.py
tests/Timer.py
tests/__init__.py
tests/helpers.py
