Metadata-Version: 2.0
Name: circuits-bricks
Version: 0.4.4
Summary: General purpose components extending the circuits framework.
Home-page: http://packages.python.org/circuits-bricks
Author: Michael N. Lipp
Author-email: mnl@mnl.de
License: MIT
Keywords: circuits component
Platform: UNKNOWN
Classifier: Development Status :: 3 - Alpha
Classifier: License :: OSI Approved :: MIT License
Requires-Dist: circuits (>=3.2)
